cvttf_NotoSansCJK_Black/NotoSansCJKtc-Black.otf
cvttf_NotoSansCJK_Black/__init__.py
cvttf_NotoSansCJK_Black-1.0.data/data/NotoSansCJKtc-Black.otf
cvttf_NotoSansCJK_Black-1.0.dist-info/DESCRIPTION.rst
cvttf_NotoSansCJK_Black-1.0.dist-info/METADATA
cvttf_NotoSansCJK_Black-1.0.dist-info/RECORD
cvttf_NotoSansCJK_Black-1.0.dist-info/WHEEL
cvttf_NotoSansCJK_Black-1.0.dist-info/metadata.json
cvttf_NotoSansCJK_Black-1.0.dist-info/top_level.txt
